cuid2-1.3.0.dist-info/METADATA
cuid2-1.3.0.dist-info/WHEEL
cuid2-1.3.0.dist-info/licenses/LICENSE
cuid2/__init__.py
cuid2/generator.py
cuid2/py.typed
cuid2/utils.py
cuid2-1.3.0.dist-info/RECORD
