Metadata-Version: 2.1
Name: cuid2
Version: 1.3.0
Summary: Next generation GUIDs. Collision-resistant ids optimized for horizontal scaling and performance.
Keywords: crypt security uuid guid cuid cryptography
Author-Email: Will Gordon <wgordon@redhat.com>
License: The MIT License (MIT)
Classifier: Development Status :: 5 - Production/Stable
Classifier: Intended Audience :: Developers
Classifier: License :: OSI Approved :: MIT License
Classifier: Operating System :: OS Independent
Classifier: Programming Language :: Python :: 3
Classifier: Programming Language :: Python :: 3.8
Classifier: Topic :: Security :: Cryptography
Classifier: Typing :: Typed
Project-URL: Repository, https://github.com/gordon-code/cuid2/
Requires-Python: >=3.8
